moesifpythonrequest/__init__.py
moesifpythonrequest/global_variables.py
moesifpythonrequest/outgoing_recorder/__init__.py
moesifpythonrequest/outgoing_recorder/outgoing_recorder.py
moesifpythonrequest/patch_request/__init__.py
moesifpythonrequest/patch_request/patch_request.py
moesifpythonrequest/send_moesif/__init__.py
moesifpythonrequest/send_moesif/send_moesif.py
moesifpythonrequest/start_capture/__init__.py
moesifpythonrequest/start_capture/start_capture.py
moesifpythonrequest/utility_function/__init__.py
moesifpythonrequest/utility_function/utility_function.py
moesifpythonrequest-0.3.5.dist-info/licenses/LICENSE
moesifpythonrequest-0.3.5.dist-info/METADATA
moesifpythonrequest-0.3.5.dist-info/WHEEL
moesifpythonrequest-0.3.5.dist-info/top_level.txt
moesifpythonrequest-0.3.5.dist-info/RECORD
